voihla/__init__.py
voihla/analysis.py
voihla/core.py
voihla/eplet.py
voihla/plotting.py
voihla/preprocessing.py
voihla/utils.py
voihla-0.1.0.dist-info/licenses/LICENSE
voihla-0.1.0.dist-info/METADATA
voihla-0.1.0.dist-info/WHEEL
voihla-0.1.0.dist-info/top_level.txt
voihla-0.1.0.dist-info/RECORD
