Metadata-Version: 2.4
Name: voihla
Version: 0.1.0
Summary: HLA Imputation Validation Package
Author: Alyssa Paynter
Author-email: Alyssa Paynter <apaynter@tulane.edu>
License-Expression: MIT
Requires-Python: >=3.8
License-File: LICENSE
Requires-Dist: pandas>=1.3.0
Requires-Dist: numpy>=1.20.0
Requires-Dist: scikit-learn>=1.0.0
Requires-Dist: matplotlib>=3.3.0
Requires-Dist: requests>=2.25.0
Requires-Dist: py-ard>=1.0.0
Dynamic: author
Dynamic: license-file
Dynamic: requires-python
